mm_result/__init__.py
mm_result/py.typed
mm_result/pydantic_support.py
mm_result/result.py
mm_result-0.2.0.dist-info/METADATA
mm_result-0.2.0.dist-info/WHEEL
mm_result-0.2.0.dist-info/RECORD
