Metadata-Version: 2.4
Name: mm-result
Version: 0.2.0
Summary: Rust-inspired Result[T] container for functional error handling in Python with optional extra metadata field
Keywords: error-handling,functional,monads,result,rust
Requires-Python: >=3.14
